powertrack_sdk/__init__.py
powertrack_sdk/auth.py
powertrack_sdk/client.py
powertrack_sdk/exceptions.py
powertrack_sdk/models.py
powertrack_sdk/mostRecentFetch.js
powertrack_sdk/utils.py
powertrack_sdk-1.0.5.dist-info/licenses/LICENSE
powertrack_sdk-1.0.5.dist-info/METADATA
powertrack_sdk-1.0.5.dist-info/WHEEL
powertrack_sdk-1.0.5.dist-info/top_level.txt
powertrack_sdk-1.0.5.dist-info/RECORD
