Metadata-Version: 2.4
Name: powertrack_sdk
Version: 1.0.5
Summary: Python SDK for AlsoEnergy PowerTrack webapp API
License: Copyright 2025 Joshua Hamsa
Project-URL: Homepage, https://github.com/dsd-hamsa/powertrack-sdk
Project-URL: Documentation, https://powertrack-sdk.readthedocs.io/
Project-URL: Repository, https://github.com/dsd-hamsa/powertrack-sdk
Project-URL: Issues, https://github.com/dsd-hamsa/powertrack-sdk/issues
Project-URL: Changelog, https://github.com/dsd-hamsa/powertrack-sdk/blob/main/CHANGELOG.md
Keywords: powertrack,alsoenergy,api,sdk,solar,monitoring
Classifier: Development Status :: 4 - Beta
Classifier: Intended Audience :: Developers
Classifier: Operating System :: OS Independent
Classifier: Programming Language :: Python :: 3
Classifier: Programming Language :: Python :: 3.8
Classifier: Programming Language :: Python :: 3.9
Classifier: Programming Language :: Python :: 3.10
Classifier: Programming Language :: Python :: 3.11
Classifier: Programming Language :: Python :: 3.12
Classifier: Topic :: Software Development :: Libraries :: Python Modules
Classifier: Topic :: System :: Monitoring
Requires-Python: >=3.8
License-File: LICENSE
Requires-Dist: requests>=2.25.0
Requires-Dist: python-dotenv>=0.10.2
Provides-Extra: dev
Requires-Dist: pytest>=7.0; extra == "dev"
Requires-Dist: pytest-cov; extra == "dev"
Requires-Dist: ruff; extra == "dev"
Requires-Dist: mypy; extra == "dev"
Requires-Dist: build; extra == "dev"
Provides-Extra: docs
Requires-Dist: sphinx>=4.0; extra == "docs"
Requires-Dist: sphinx-rtd-theme>=1.0.0; extra == "docs"
Dynamic: license-file
